api_hour/__init__.py
api_hour/application.py
api_hour/config.py
api_hour/container.py
api_hour/utils.py
api_hour/worker.py
api_hour/plugins/__init__.py
api_hour/plugins/aiohttp/__init__.py
api_hour/plugins/aiohttp/environment.py
api_hour/plugins/aiohttp/response.py
api_hour/plugins/aiohttp/router.py
api_hour-0.8.2.dist-info/DESCRIPTION.rst
api_hour-0.8.2.dist-info/METADATA
api_hour-0.8.2.dist-info/RECORD
api_hour-0.8.2.dist-info/WHEEL
api_hour-0.8.2.dist-info/entry_points.txt
api_hour-0.8.2.dist-info/metadata.json
api_hour-0.8.2.dist-info/top_level.txt
test/__init__.py
test/plugins/__init__.py
test/plugins/aiohttp/__init__.py
test/plugins/aiohttp/test_serialize.py
