Metadata-Version: 2.0
Name: api-hour
Version: 0.8.2
Summary: Write efficient network daemons (HTTP, SSH...) with ease.
Home-page: http://www.api-hour.io
Author: Eyepea Dev Team
Author-email: gmludo@gmail.com
License: Apache 2
Download-URL: https://pypi.python.org/pypi/api_hour
Keywords: asyncio,performance,efficient,web,service,rest,json,daemon,application
Platform: OS Independent
Classifier: Development Status :: 5 - Production/Stable
Classifier: Environment :: No Input/Output (Daemon)
Classifier: Environment :: Web Environment
Classifier: Intended Audience :: Developers
Classifier: License :: OSI Approved :: Apache Software License
Classifier: Natural Language :: English
Classifier: Operating System :: OS Independent
Classifier: Programming Language :: Python
Classifier: Programming Language :: Python :: 3
Classifier: Programming Language :: Python :: 3.5
Classifier: Programming Language :: Python :: 3 :: Only
Classifier: Programming Language :: Python :: Implementation :: CPython
Classifier: Topic :: Internet :: WWW/HTTP
Classifier: Topic :: Internet :: WWW/HTTP :: Dynamic Content
Classifier: Topic :: Internet :: WWW/HTTP :: HTTP Servers
Classifier: Topic :: System :: Networking
Provides: api_hour
Requires-Dist: gunicorn
Requires-Dist: PyYAML
Requires-Dist: setproctitle
